pysps/__init__.py
pysps/inclusion_prob.py
pysps/order_sample.py
pysps-0.1.1.dist-info/licenses/LICENSE
pysps-0.1.1.dist-info/METADATA
pysps-0.1.1.dist-info/WHEEL
pysps-0.1.1.dist-info/top_level.txt
pysps-0.1.1.dist-info/RECORD
