Metadata-Version: 2.4
Name: pysps
Version: 0.1.1
Summary: Sequential Poisson sampling for Python.
Author-email: Steve Martin <marberts@protonmail.com>
License-Expression: MIT
Classifier: Intended Audience :: Science/Research
Classifier: Programming Language :: Python :: 3
Requires-Python: >=3.10
License-File: LICENSE
Requires-Dist: numpy>=2.2.2
Dynamic: license-file
